fuzzywuzzymit/__init__.py
fuzzywuzzymit/fuzz.py
fuzzywuzzymit/process.py
fuzzywuzzymit/string_processing.py
fuzzywuzzymit/utils.py
fuzzywuzzymit-0.0.2.dist-info/DESCRIPTION.rst
fuzzywuzzymit-0.0.2.dist-info/METADATA
fuzzywuzzymit-0.0.2.dist-info/RECORD
fuzzywuzzymit-0.0.2.dist-info/WHEEL
fuzzywuzzymit-0.0.2.dist-info/metadata.json
fuzzywuzzymit-0.0.2.dist-info/top_level.txt
fuzzywuzzymit-0.0.2.dist-info/zip-safe
