Metadata-Version: 2.0
Name: fuzzywuzzymit
Version: 0.0.2
Summary: Fuzzy string matching in python
Home-page: https://github.com/graingert/fuzzywuzzymit
Author: Adam Cohen
Author-email: adam@seatgeek.com
License: MIT
Platform: UNKNOWN
Classifier: Intended Audience :: Developers
Classifier: Programming Language :: Python
Classifier: Programming Language :: Python :: 2.6
Classifier: Programming Language :: Python :: 2.7
Classifier: Programming Language :: Python :: 3
Classifier: Programming Language :: Python :: 3.3
Classifier: Programming Language :: Python :: 3.4
Classifier: Programming Language :: Python :: 3.5
Classifier: Programming Language :: Python :: 3.6
